y42/__init__.py
y42/api.py
y42/cli/__init__.py
y42/cli/app.py
y42/cli/client.py
y42/cli/settings.py
y42/cli/state.py
y42/cli/util.py
y42/clients/__init__.py
y42/clients/company.py
y42/clients/space.py
y42/clients/y42.py
y42/models/__init__.py
y42/models/company.py
y42/models/space.py
y42/models/util.py
y42-0.0.3.dist-info/entry_points.txt
y42-0.0.3.dist-info/LICENSE
y42-0.0.3.dist-info/WHEEL
y42-0.0.3.dist-info/METADATA
y42-0.0.3.dist-info/RECORD
