Metadata-Version: 2.1
Name: y42
Version: 0.0.3
Summary: Client for programmatic usage of Y42
License: Apache-2.0
Author: Y42
Author-email: support@y42.com
Requires-Python: >=3.10,<4.0
Classifier: License :: OSI Approved :: Apache Software License
Classifier: Programming Language :: Python :: 3
Classifier: Programming Language :: Python :: 3.10
Classifier: Programming Language :: Python :: 3.11
Requires-Dist: httpx (>=0.23.3,<0.24.0)
Requires-Dist: pydantic (>=1.10.4,<2.0.0)
Requires-Dist: python-dotenv (>=0.21.1,<0.22.0)
Requires-Dist: typer[all] (>=0.7.0,<0.8.0)
